{"diff_netsenders_30": -80, "diff_netsenders_365": 856, "diff_netsenders_7": -55, "diff_netsent_30": -2779, "diff_netsent_365": 31627, "diff_netsent_7": -715, "first_date": "2015-10-25", "last_date": "2016-06-08", "percentage_senders_30": 30, "percentage_senders_365": 0, "percentage_senders_7": 100, "percentage_sent_30": 39, "percentage_sent_365": 0, "percentage_sent_7": 100, "repositories": 1, "senders": 856, "senders_30": 185, "senders_365": 856, "senders_7": 0, "sent": 31627, "sent_30": 4339, "sent_365": 31627, "sent_7": 0}