{"diff_netsenders_30": -23, "diff_netsenders_365": 659, "diff_netsenders_7": -8, "diff_netsent_30": -1185, "diff_netsent_365": -37895, "diff_netsent_7": -687, "first_date": "2012-07-03", "last_date": "2015-01-23", "percentage_senders_30": 10, "percentage_senders_365": 53, "percentage_senders_7": 8, "percentage_sent_30": 26, "percentage_sent_365": 34, "percentage_sent_7": 45, "repositories": 1, "senders": 3112, "senders_30": 203, "senders_365": 1901, "senders_7": 84, "sent": 247224, "sent_30": 3368, "sent_365": 73366, "sent_7": 832}