{"actions": 163986, "added_lines": 5582804.0, "added_lines_30": 25974.0, "added_lines_365": 1515409.0, "added_lines_7": 2331.0, "authors": 487, "authors_30": 52, "authors_365": 261, "authors_7": 19, "avg_commits_author": 126.53, "avg_commits_month": 451.22, "avg_files_author": 81.64, "avg_files_month": 291.14, "branches": 1448, "commits": 61366, "commits_30": 866, "commits_365": 19437, "commits_7": 93, "committers": 487, "diff_netadded_lines_30": -33189.0, "diff_netadded_lines_365": 658109.0, "diff_netadded_lines_7": -5776.0, "diff_netauthors_30": -16, "diff_netauthors_365": 94, "diff_netauthors_7": -13, "diff_netcommits_30": -895, "diff_netcommits_365": 8475, "diff_netcommits_7": -88, "diff_netfiles_30": -1003, "diff_netfiles_365": 4391, "diff_netfiles_7": -57, "diff_netnewauthors_30": -3, "diff_netnewauthors_365": 60, "diff_netnewauthors_7": -3, "diff_netremoved_lines_30": -14866.0, "diff_netremoved_lines_365": 464973.0, "diff_netremoved_lines_7": -720.0, "files": 39595, "files_30": 589, "files_365": 15411, "files_7": 111, "first_date": "2004-06-24", "last_date": "2015-10-30", "newauthors": 487, "newauthors_30": 8, "newauthors_365": 179, "newauthors_7": 0, "percentage_added_lines_30": 56, "percentage_added_lines_365": 76, "percentage_added_lines_7": 71, "percentage_authors_30": 23, "percentage_authors_365": 56, "percentage_authors_7": 40, "percentage_commits_30": 50, "percentage_commits_365": 77, "percentage_commits_7": 48, "percentage_files_30": 63, "percentage_files_365": 39, "percentage_files_7": 33, "percentage_newauthors_30": 27, "percentage_newauthors_365": 50, "percentage_newauthors_7": 100, "percentage_removed_lines_30": 58, "percentage_removed_lines_365": 155, "percentage_removed_lines_7": 30, "removed_lines": 3597157.0, "removed_lines_30": 10375.0, "removed_lines_365": 763825.0, "removed_lines_7": 1615.0, "repositories": 1}