{"actions": 19495, "added_lines": 236344.0, "added_lines_30": 6141.0, "added_lines_365": 71531.0, "added_lines_7": 429.0, "authors": 57, "authors_30": 14, "authors_365": 36, "authors_7": 9, "avg_commits_author": 99.41, "avg_commits_month": 107.06, "avg_files_author": 166.84, "avg_files_month": 179.67, "branches": 270, "commits": 5567, "commits_30": 241, "commits_365": 1916, "commits_7": 54, "committers": 57, "diff_netadded_lines_30": -848.0, "diff_netadded_lines_365": -33300.0, "diff_netadded_lines_7": -1117.0, "diff_netauthors_30": -4, "diff_netauthors_365": 15, "diff_netauthors_7": 0, "diff_netcommits_30": 53, "diff_netcommits_365": 469, "diff_netcommits_7": 19, "diff_netfiles_30": -45, "diff_netfiles_365": -481, "diff_netfiles_7": 16, "diff_netnewauthors_30": -1, "diff_netnewauthors_365": 2, "diff_netnewauthors_7": 0, "diff_netremoved_lines_30": 1452.0, "diff_netremoved_lines_365": -114879.0, "diff_netremoved_lines_7": -194.0, "files": 9343, "files_30": 322, "files_365": 4077, "files_7": 70, "first_date": "2011-05-18", "last_date": "2015-10-17", "newauthors": 57, "newauthors_30": 0, "newauthors_365": 11, "newauthors_7": 0, "percentage_added_lines_30": 12, "percentage_added_lines_365": 31, "percentage_added_lines_7": 72, "percentage_authors_30": 22, "percentage_authors_365": 71, "percentage_authors_7": 0, "percentage_commits_30": 28, "percentage_commits_365": 32, "percentage_commits_7": 54, "percentage_files_30": 12, "percentage_files_365": 10, "percentage_files_7": 29, "percentage_newauthors_30": 100, "percentage_newauthors_365": 22, "percentage_newauthors_7": 0, "percentage_removed_lines_30": 114, "percentage_removed_lines_365": 79, "percentage_removed_lines_7": 64, "removed_lines": 199309.0, "removed_lines_30": 2717.0, "removed_lines_365": 28850.0, "removed_lines_7": 109.0, "repositories": 1}