{"diff_netsenders_30": 1, "diff_netsenders_365": 2, "diff_netsenders_7": 0, "diff_netsent_30": 20, "diff_netsent_365": 15, "diff_netsent_7": -6, "first_date": "2010-07-17", "last_date": "2015-07-01", "percentage_senders_30": 100, "percentage_senders_365": 40, "percentage_senders_7": 0, "percentage_sent_30": 500, "percentage_sent_365": 8, "percentage_sent_7": 60, "senders": 9, "senders_30": 2, "senders_365": 7, "senders_7": 1, "senders_init": 6, "senders_response": 8, "sent": 406, "sent_30": 24, "sent_365": 200, "sent_7": 4, "sent_response": 332, "threads": 74}