{"diff_netsenders_30": 5, "diff_netsenders_365": 26, "diff_netsenders_7": 0, "diff_netsent_30": 55, "diff_netsent_365": 232, "diff_netsent_7": -10, "first_date": "2009-11-06", "last_date": "2015-06-03", "percentage_senders_30": 35, "percentage_senders_365": 31, "percentage_senders_7": 0, "percentage_sent_30": 117, "percentage_sent_365": 49, "percentage_sent_7": 41, "senders": 1, "senders_30": 19, "senders_365": 108, "senders_7": 8, "senders_init": 1, "senders_response": 1, "sent": 557, "sent_30": 102, "sent_365": 697, "sent_7": 14, "sent_response": 490, "threads": 67}