{"diff_netsenders_30": 31, "diff_netsenders_365": 188, "diff_netsenders_7": 0, "diff_netsent_30": 6, "diff_netsent_365": 1807, "diff_netsent_7": -28, "first_date": "2009-10-15", "last_date": "2015-02-22", "percentage_senders_30": 25, "percentage_senders_365": 32, "percentage_senders_7": 0, "percentage_sent_30": 1, "percentage_sent_365": 36, "percentage_sent_7": 20, "repositories": 2, "senders": 1186, "senders_30": 154, "senders_365": 774, "senders_7": 50, "senders_init": 1026, "senders_response": 825, "sent": 14360, "sent_30": 536, "sent_365": 6753, "sent_7": 106, "sent_response": 10062, "threads": 4298}