{"senders.": {"id": [48, 5, 61, 43, 222, 226, 374, 1126, 186, 124], "senders": ["Greg Farnum", "Sage Weil", "Wido den Hollander", "Yehuda Sadeh", "markhpc", "Alfredo Deza", "Craig Lewis", "Christian Balzer", "Loic Dachary", "Joao Eduardo Luis"], "sent": [742, 354, 273, 241, 225, 220, 173, 144, 138, 132]}, "senders.last month": {"id": [48, 5, 61, 1126, 69, 374, 791, 156, 226, 222], "senders": ["Greg Farnum", "Sage Weil", "Wido den Hollander", "Christian Balzer", "Samuel Just", "Craig Lewis", "Andrija Panic", "Sylvain Munaut", "Alfredo Deza", "markhpc"], "sent": [75, 31, 29, 22, 20, 19, 17, 17, 15, 15]}, "senders.last year": {"id": [48, 5, 226, 61, 43, 374, 222, 1126, 186, 702], "senders": ["Greg Farnum", "Sage Weil", "Alfredo Deza", "Wido den Hollander", "Yehuda Sadeh", "Craig Lewis", "markhpc", "Christian Balzer", "Loic Dachary", "karan singh"], "sent": [509, 249, 220, 209, 171, 163, 155, 144, 135, 97]}}