{"diff_netsenders_30": 17, "diff_netsenders_365": 13, "diff_netsenders_7": 5, "diff_netsent_30": 176, "diff_netsent_365": -671, "diff_netsent_7": -13, "first_date": "2009-10-15", "last_date": "2015-02-17", "percentage_senders_30": 22, "percentage_senders_365": 3, "percentage_senders_7": 14, "percentage_sent_30": 46, "percentage_sent_365": 12, "percentage_sent_7": 9, "repositories": 1, "senders": 1176, "senders_30": 91, "senders_365": 424, "senders_7": 40, "senders_init": 831, "senders_response": 849, "sent": 23373, "sent_30": 558, "sent_365": 4745, "sent_7": 130, "sent_response": 18231, "threads": 5142}