{"diff_netsenders_30": -1, "diff_netsenders_365": 205, "diff_netsenders_7": -6, "diff_netsent_30": 304, "diff_netsent_365": 1774, "diff_netsent_7": 24, "first_date": "2013-02-24", "last_date": "2015-09-10", "percentage_senders_30": 0, "percentage_senders_365": 24, "percentage_senders_7": 6, "percentage_sent_30": 40, "percentage_sent_365": 20, "percentage_sent_7": 8, "senders": 1830, "senders_30": 203, "senders_365": 1049, "senders_7": 93, "senders_init": 1546, "senders_response": 1315, "sent": 22964, "sent_30": 1060, "sent_365": 10520, "sent_7": 315, "sent_response": 17338, "threads": 5626}