{"changed": 14297, "changed_30": 633, "changed_365": 4529, "changed_7": 276, "changers": 344, "changers_30": 46, "changers_365": 136, "changers_7": 25, "closed": 12632, "closed_30": 372, "closed_365": 3055, "closed_7": 180, "closers": 86, "closers_30": 23, "closers_365": 57, "closers_7": 6, "diff_netchanged_30": 236, "diff_netchanged_365": 1335, "diff_netchanged_7": 54, "diff_netchangers_30": 5, "diff_netchangers_365": 21, "diff_netchangers_7": -5, "diff_netclosed_30": 197, "diff_netclosed_365": 628, "diff_netclosed_7": 87, "diff_netclosers_30": 5, "diff_netclosers_365": 16, "diff_netclosers_7": -6, "diff_netopened_30": 104, "diff_netopened_365": 558, "diff_netopened_7": -4, "diff_netopeners_30": 14, "diff_netopeners_365": 96, "diff_netopeners_7": 4, "opened": 15319, "opened_30": 350, "opened_365": 3627, "opened_7": 79, "openers": 1027, "openers_30": 79, "openers_365": 432, "openers_7": 32, "percentage_changed_30": 59, "percentage_changed_365": 41, "percentage_changed_7": 24, "percentage_changers_30": 12, "percentage_changers_365": 18, "percentage_changers_7": 16, "percentage_closed_30": 112, "percentage_closed_365": 25, "percentage_closed_7": 93, "percentage_closers_30": 27, "percentage_closers_365": 39, "percentage_closers_7": 50, "percentage_opened_30": 42, "percentage_opened_365": 18, "percentage_opened_7": 4, "percentage_openers_30": 21, "percentage_openers_365": 28, "percentage_openers_7": 14, "trackers": 1}