{"diff_netsenders_30": -3, "diff_netsenders_365": 47, "diff_netsenders_7": 6, "diff_netsent_30": 48, "diff_netsent_365": 489, "diff_netsent_7": 11, "first_date": "2009-10-15", "last_date": "2016-06-27", "percentage_senders_30": 3, "percentage_senders_365": 10, "percentage_senders_7": 18, "percentage_sent_30": 9, "percentage_sent_365": 8, "percentage_sent_7": 9, "senders": 1580, "senders_30": 87, "senders_365": 495, "senders_7": 39, "senders_init": 1116, "senders_response": 1136, "sent": 31958, "sent_30": 542, "sent_365": 6244, "sent_7": 129, "sent_response": 24906, "threads": 7052}