{"actions": 15754, "added_lines": 477341.0, "added_lines_30": 69349, "added_lines_365": 1629362, "added_lines_7": 16382, "authors": 22, "authors_30": 10, "authors_365": 16, "authors_7": 8, "avg_commits_author": 295.2273, "avg_commits_month": 103.0952, "avg_files_author": 294.8182, "avg_files_month": 102.9524, "branches": 367, "commits": 6495, "commits_30": 349, "commits_365": 2962, "commits_7": 146, "committers": 21, "diff_netadded_lines_30": -417920, "diff_netadded_lines_365": 1141381, "diff_netadded_lines_7": 5193, "diff_netauthors_30": 2, "diff_netauthors_365": 0, "diff_netauthors_7": 3, "diff_netcommits_30": -204, "diff_netcommits_365": 1519, "diff_netcommits_7": 81, "diff_netfiles_30": -88, "diff_netfiles_365": 2648, "diff_netfiles_7": 158, "diff_netremoved_lines_30": -704223, "diff_netremoved_lines_365": 1167131, "diff_netremoved_lines_7": 1180, "files": 6486, "files_30": 553, "files_365": 4402, "files_7": 226, "first_date": "2004-06-24", "last_date": "2014-09-27", "percentage_added_lines_30": 85, "percentage_added_lines_365": 233, "percentage_added_lines_7": 46, "percentage_authors_30": 25, "percentage_authors_365": 0, "percentage_authors_7": 60, "percentage_commits_30": 36, "percentage_commits_365": 105, "percentage_commits_7": 124, "percentage_files_30": 13, "percentage_files_365": 150, "percentage_files_7": 232, "percentage_removed_lines_30": 97, "percentage_removed_lines_365": 461, "percentage_removed_lines_7": 33, "removed_lines": 204079.0, "removed_lines_30": 21113, "removed_lines_365": 1419826, "removed_lines_7": 4661, "repositories": 16}