{"senders.": {"senders": ["Yan, Zheng", "majianpeng", "Xiaoxi Chen", "Tony Butler", "xinxinshu", "stephen.l.blinick@intel.com", "jian.zhang@intel.com", "jiangang.duan@intel.com", "dunk007-Re5JQEeQqe8AvxtiuMwx3w@public.gmane.org", "kirill.shutemov-VuQAYsv1563Yd54FQh9/CA@public.gmane.org", "xiwei.huang@intel.com", "nigel.cook@intel.com", "chendi.xue@intel.com", "sean.hefty@intel.com", "jdmason-zqedIHPRSYI@public.gmane.org", "fengguang.wu@intel.com", "yujie.he@intel.com", "aaron.f.brown@intel.com"], "sent": [681, 125, 59, 42, 39, 14, 9, 9, 8, 7, 6, 6, 6, 3, 3, 2, 2, 1]}, "senders.last month": {"senders": ["Yan, Zheng", "majianpeng", "Xiaoxi Chen", "Tony Butler", "xinxinshu", "stephen.l.blinick@intel.com", "jian.zhang@intel.com", "jiangang.duan@intel.com", "dunk007-Re5JQEeQqe8AvxtiuMwx3w@public.gmane.org", "kirill.shutemov-VuQAYsv1563Yd54FQh9/CA@public.gmane.org", "xiwei.huang@intel.com", "nigel.cook@intel.com", "chendi.xue@intel.com", "sean.hefty@intel.com", "jdmason-zqedIHPRSYI@public.gmane.org", "fengguang.wu@intel.com", "yujie.he@intel.com", "aaron.f.brown@intel.com"], "sent": [681, 125, 59, 42, 39, 14, 9, 9, 8, 7, 6, 6, 6, 3, 3, 2, 2, 1]}, "senders.last year": {"senders": ["Yan, Zheng", "majianpeng", "Xiaoxi Chen", "Tony Butler", "xinxinshu", "stephen.l.blinick@intel.com", "jian.zhang@intel.com", "jiangang.duan@intel.com", "dunk007-Re5JQEeQqe8AvxtiuMwx3w@public.gmane.org", "kirill.shutemov-VuQAYsv1563Yd54FQh9/CA@public.gmane.org", "xiwei.huang@intel.com", "nigel.cook@intel.com", "chendi.xue@intel.com", "sean.hefty@intel.com", "jdmason-zqedIHPRSYI@public.gmane.org", "fengguang.wu@intel.com", "yujie.he@intel.com", "aaron.f.brown@intel.com"], "sent": [681, 125, 59, 42, 39, 14, 9, 9, 8, 7, 6, 6, 6, 3, 3, 2, 2, 1]}}