{"diff_netsenders_30": -57, "diff_netsenders_365": 713, "diff_netsenders_7": 37, "diff_netsent_30": -2496, "diff_netsent_365": -23681, "diff_netsent_7": 1618, "first_date": "2012-07-03", "last_date": "2014-12-21", "percentage_senders_30": 17, "percentage_senders_365": 56, "percentage_senders_7": 56, "percentage_sent_30": 29, "percentage_sent_365": 18, "percentage_sent_7": 261, "repositories": 3, "senders": 3140, "senders_30": 262, "senders_365": 1977, "senders_7": 102, "sent": 287992, "sent_30": 5899, "sent_365": 104904, "sent_7": 2237}