{"senders.": {"id": [126, 124, 5, 69, 222, 186, 2374, 226, 710, 2711], "senders": ["Dan Mick", "Joao Eduardo Luis", "Sage Weil", "Samuel Just", "Mark Nelson", "Loic Dachary", "gregaf", "Alfredo Deza", "Alphe Salas Michels", "joshd"], "sent": [10451, 8427, 8368, 7723, 5994, 5482, 5146, 4697, 3818, 3097]}, "senders.last month": {"id": [226, 2349, 4501, 69, 5, 48, 2592, 124, 4047, 186], "senders": ["Alfredo Deza", "ghartz", "steveeJ", "Samuel Just", "Sage Weil", "Greg Farnum", "iggy", "Joao Eduardo Luis", "bens", "Loic Dachary"], "sent": [357, 298, 296, 291, 280, 278, 206, 197, 191, 189]}, "senders.last year": {"id": [5, 186, 126, 226, 69, 124, 710, 48, 3003, 222], "senders": ["Sage Weil", "Loic Dachary", "Dan Mick", "Alfredo Deza", "Samuel Just", "Joao Eduardo Luis", "Alphe Salas Michels", "Greg Farnum", "mozg", "Mark Nelson"], "sent": [5903, 5062, 4758, 4697, 4662, 3859, 3563, 2758, 2427, 2105]}}