{"diff_netsenders_30": -30, "diff_netsenders_365": 500, "diff_netsenders_7": 7, "diff_netsent_30": -1767, "diff_netsent_365": -15147, "diff_netsent_7": 74, "first_date": "2012-07-03", "last_date": "2015-07-17", "percentage_senders_30": 9, "percentage_senders_365": 34, "percentage_senders_7": 6, "percentage_sent_30": 11, "percentage_sent_365": 12, "percentage_sent_7": 2, "repositories": 3, "senders": 3678, "senders_30": 289, "senders_365": 1942, "senders_7": 116, "sent": 348941, "sent_30": 13010, "sent_365": 107452, "sent_7": 3514}