{"senders.": {"id": [226765, 227784, 228090, 226237, 228450, 227108, 228830, 228837, 226252, 227834], "senders": ["dmick", "joao", "loicd", "alfredodeza", "nhm", "gregaf", "sage", "sagewk", "alphe", "joshd"], "sent": [11782, 10029, 9527, 6182, 5225, 5146, 4918, 3949, 3892, 3407]}, "senders.last month": {"id": [228090, 229451, 226431, 228969, 227784, 226237, 228830, 228973, 227799, 228373], "senders": ["loicd", "xoritor", "bloodice", "sjusthm", "joao", "alfredodeza", "sage", "sjustwork", "joelio", "mourgaya"], "sent": [1231, 1085, 703, 477, 440, 414, 414, 377, 327, 243]}, "senders.last year": {"id": [228090, 226237, 227784, 226765, 228830, 227115, 226252, 228969, 227971, 228884], "senders": ["loicd", "alfredodeza", "joao", "dmick", "sage", "gregsfortytwo", "alphe", "sjusthm", "kraken", "scuttlemonkey"], "sent": [7019, 3964, 3332, 3115, 3099, 2585, 2194, 2011, 1363, 1277]}}