{"diff_netsenders_30": -2, "diff_netsenders_365": 178, "diff_netsenders_7": -16, "diff_netsent_30": -150, "diff_netsent_365": 2615, "diff_netsent_7": -61, "domains": 458, "first_date": "2009-10-15", "last_date": "2015-06-26", "organizations": 120, "percentage_senders_30": 0, "percentage_senders_365": 16, "percentage_senders_7": 14, "percentage_sent_30": 10, "percentage_sent_365": 20, "percentage_sent_7": 18, "senders": 2592, "senders_30": 261, "senders_365": 1248, "senders_7": 98, "senders_init": 2119, "senders_response": 1840, "sent": 45657, "sent_30": 1259, "sent_365": 15220, "sent_7": 263, "sent_response": 35098, "threads": 10559}