{"actions": 188331, "added_lines": 5431578.0, "added_lines_30": 120264.0, "added_lines_365": 2327897.0, "added_lines_7": 53410.0, "authors": 110, "authors_30": 42, "authors_365": 84, "authors_7": 27, "avg_commits_author": 591.55, "avg_commits_month": 774.64, "avg_files_author": 767.2, "avg_files_month": 1004.67, "branches": 3022, "commits": 62164, "commits_30": 872, "commits_365": 23095, "commits_7": 179, "committers": 104, "diff_netadded_lines_30": 69528.0, "diff_netadded_lines_365": 277076.0, "diff_netadded_lines_7": 48150.0, "diff_netauthors_30": 6, "diff_netauthors_365": 16, "diff_netauthors_7": 5, "diff_netcommits_30": 185, "diff_netcommits_365": -3736, "diff_netcommits_7": -33, "diff_netfiles_30": 1084, "diff_netfiles_365": 17837, "diff_netfiles_7": 475, "diff_netnewauthors_30": 0, "diff_netnewauthors_365": 1, "diff_netnewauthors_7": 0, "diff_netremoved_lines_30": -4243.0, "diff_netremoved_lines_365": -10928.0, "diff_netremoved_lines_7": -457.0, "files": 84392, "files_30": 2243, "files_365": 43661, "files_7": 829, "first_date": "2010-02-09", "last_date": "2017-02-14", "newauthors": 110, "newauthors_30": 0, "newauthors_365": 28, "newauthors_7": 0, "percentage_added_lines_30": 137, "percentage_added_lines_365": 13, "percentage_added_lines_7": 915, "percentage_authors_30": 16, "percentage_authors_365": 23, "percentage_authors_7": 22, "percentage_commits_30": 26, "percentage_commits_365": 13, "percentage_commits_7": 15, "percentage_files_30": 93, "percentage_files_365": 69, "percentage_files_7": 134, "percentage_newauthors_30": 0, "percentage_newauthors_365": 3, "percentage_newauthors_7": 0, "percentage_removed_lines_30": 18, "percentage_removed_lines_365": 1, "percentage_removed_lines_7": 11, "removed_lines": 2732167.0, "removed_lines_30": 19106.0, "removed_lines_365": 848079.0, "removed_lines_7": 3399.0, "repositories": 25}