{"diff_netsenders_30": 9, "diff_netsenders_365": 13, "diff_netsenders_7": -2, "diff_netsent_30": -65, "diff_netsent_365": 682, "diff_netsent_7": -7, "first_date": "2009-10-22", "last_date": "2016-03-17", "percentage_senders_30": 30, "percentage_senders_365": 21, "percentage_senders_7": 10, "percentage_sent_30": 15, "percentage_sent_365": 18, "percentage_sent_7": 9, "senders": 103, "senders_30": 39, "senders_365": 74, "senders_7": 17, "senders_init": 49, "senders_response": 99, "sent": 8983, "sent_30": 350, "sent_365": 4405, "sent_7": 67, "sent_response": 7740, "threads": 1243}