{"actions": 182587, "added_lines": 5240902.0, "added_lines_30": 264828.0, "added_lines_365": 2604649.0, "added_lines_7": 702.0, "authors": 110, "authors_30": 44, "authors_365": 86, "authors_7": 17, "avg_commits_author": 576.21, "avg_commits_month": 772.96, "avg_files_author": 742.05, "avg_files_month": 995.43, "branches": 2935, "commits": 60477, "commits_30": 1067, "commits_365": 26216, "commits_7": 63, "committers": 104, "diff_netadded_lines_30": 104563.0, "diff_netadded_lines_365": 657120.0, "diff_netadded_lines_7": -164907.0, "diff_netauthors_30": -2, "diff_netauthors_365": 24, "diff_netauthors_7": -7, "diff_netcommits_30": -803, "diff_netcommits_365": 2069, "diff_netcommits_7": -96, "diff_netfiles_30": 3591, "diff_netfiles_365": 21423, "diff_netfiles_7": -5543, "diff_netnewauthors_30": -3, "diff_netnewauthors_365": 14, "diff_netnewauthors_7": 0, "diff_netremoved_lines_30": 180679.0, "diff_netremoved_lines_365": 134988.0, "diff_netremoved_lines_7": -162584.0, "files": 81625, "files_30": 8442, "files_365": 45422, "files_7": 86, "first_date": "2010-02-09", "last_date": "2016-12-26", "newauthors": 110, "newauthors_30": 1, "newauthors_365": 35, "newauthors_7": 0, "percentage_added_lines_30": 65, "percentage_added_lines_365": 33, "percentage_added_lines_7": 99, "percentage_authors_30": 4, "percentage_authors_365": 38, "percentage_authors_7": 29, "percentage_commits_30": 42, "percentage_commits_365": 8, "percentage_commits_7": 60, "percentage_files_30": 74, "percentage_files_365": 89, "percentage_files_7": 98, "percentage_newauthors_30": 75, "percentage_newauthors_365": 66, "percentage_newauthors_7": 0, "percentage_removed_lines_30": 250, "percentage_removed_lines_365": 15, "percentage_removed_lines_7": 99, "removed_lines": 2684877.0, "removed_lines_30": 252918.0, "removed_lines_365": 997222.0, "removed_lines_7": 266.0, "repositories": 25}