{"actions": 161963, "added_lines": 4716855.0, "added_lines_30": 49245.0, "added_lines_365": 738082.0, "added_lines_7": 31682.0, "authors": 97, "authors_30": 1, "authors_365": 1, "authors_7": 1, "avg_commits_author": 579.79, "avg_commits_month": 677.59, "avg_files_author": 745.16, "avg_files_month": 870.86, "branches": 2761, "commits": 54304, "commits_30": 112, "commits_365": 3507, "commits_7": 39, "committers": 299, "diff_netadded_lines_30": -98450.0, "diff_netadded_lines_365": 398339.0, "diff_netadded_lines_7": 14377.0, "diff_netauthors_30": 0, "diff_netauthors_365": 0, "diff_netauthors_7": 0, "diff_netcommits_30": -101, "diff_netcommits_365": -1523, "diff_netcommits_7": 15, "diff_netfiles_30": -5217, "diff_netfiles_365": 7467, "diff_netfiles_7": 155, "diff_netnewauthors_30": -1, "diff_netnewauthors_365": -3, "diff_netnewauthors_7": 0, "diff_netremoved_lines_30": -139548.0, "diff_netremoved_lines_365": 111503.0, "diff_netremoved_lines_7": 738.0, "files": 72281, "files_30": 463, "files_365": 11369, "files_7": 302, "first_date": "2016-12-12", "last_date": "2017-02-03", "newauthors": 97, "newauthors_30": 0, "newauthors_365": 21, "newauthors_7": 0, "percentage_added_lines_30": 66, "percentage_added_lines_365": 117, "percentage_added_lines_7": 83, "percentage_authors_30": 0, "percentage_authors_365": 0, "percentage_authors_7": 0, "percentage_commits_30": 47, "percentage_commits_365": 30, "percentage_commits_7": 62, "percentage_files_30": 91, "percentage_files_365": 191, "percentage_files_7": 105, "percentage_newauthors_30": 100, "percentage_newauthors_365": 12, "percentage_newauthors_7": 0, "percentage_removed_lines_30": 93, "percentage_removed_lines_365": 75, "percentage_removed_lines_7": 212, "removed_lines": 2270904.0, "removed_lines_30": 9759.0, "removed_lines_365": 259140.0, "removed_lines_7": 1086.0, "repositories": 25}