{"actions": 44088, "added_lines": 1278300.0, "added_lines_30": 14749.0, "added_lines_365": 474399.0, "added_lines_7": 3563.0, "authors": 59, "authors_30": 1, "authors_365": 1, "authors_7": 1, "avg_commits_author": 298.31, "avg_commits_month": 262.15, "avg_files_author": 350.83, "avg_files_month": 308.3, "branches": 1059, "commits": 17267, "commits_30": 370, "commits_365": 3602, "commits_7": 49, "committers": 141, "diff_netadded_lines_30": -64465.0, "diff_netadded_lines_365": 472536.0, "diff_netadded_lines_7": -4600.0, "diff_netauthors_30": 0, "diff_netauthors_365": 0, "diff_netauthors_7": 0, "diff_netcommits_30": -87, "diff_netcommits_365": 3582, "diff_netcommits_7": -54, "diff_netfiles_30": -257, "diff_netfiles_365": 3314, "diff_netfiles_7": 17, "diff_netnewauthors_30": 0, "diff_netnewauthors_365": 3, "diff_netnewauthors_7": 0, "diff_netremoved_lines_30": -16750.0, "diff_netremoved_lines_365": 316108.0, "diff_netremoved_lines_7": -1467.0, "files": 20348, "files_30": 448, "files_365": 3344, "files_7": 134, "first_date": "2015-08-10", "last_date": "2015-08-27", "newauthors": 59, "newauthors_30": 2, "newauthors_365": 18, "newauthors_7": 0, "percentage_added_lines_30": 81, "percentage_added_lines_365": 25364, "percentage_added_lines_7": 56, "percentage_authors_30": 0, "percentage_authors_365": 0, "percentage_authors_7": 0, "percentage_commits_30": 19, "percentage_commits_365": 17910, "percentage_commits_7": 52, "percentage_files_30": 36, "percentage_files_365": 11046, "percentage_files_7": 14, "percentage_newauthors_30": 0, "percentage_newauthors_365": 20, "percentage_newauthors_7": 0, "percentage_removed_lines_30": 83, "percentage_removed_lines_365": 95790, "percentage_removed_lines_7": 83, "removed_lines": 894897.0, "removed_lines_30": 3420.0, "removed_lines_365": 316438.0, "removed_lines_7": 284.0, "repositories": 25}