{"senders.": {"senders": ["Sage Weil", "Gregory Farnum", "Loic Dachary", "Josh Durgin", "Yehuda Sadeh", "Mark Nelson", "Ilya Dryomov", "Samuel Just", "Noah Watkins", "Alfredo Deza", "Joao Eduardo Luis", "Dan Mick", "Travis Rhoden", "jcsp", "John Wilkins", "Patrick McGarry", "Jeff Layton", "David Zafman", "Ken Dreyer", "Josef Bacik", "Yuri Weinstein", "Yan, Zheng", "Kevin Wolf", "Ian Colle", "dhowells", "Daniel P. Berrange", "Avi Kivity", "Ross Turk", "Mike Christie", "Luis Pabon", "Jason Dillaman", "Brad Hubbard", "Eric Blake", "Tyler Brekke", "Douglas Fuller", "Lukas Czerner", "Mauro Carvalho Chehab", "Zack Cerza", "Mehdi Abaakouk", "Mike Snitzer", "Gregory Meno", "Kefu Chai", "Osier Yang", "Anand Avati", "Jeff Darcy", "Christopher R. Hertel", "Paolo Bonzini", "rwheeler", "Giulio Fidente", "Richard Fontana", "Benny Kopilov", "Sandon Van Ness", "Simo Sorce", "chenh", "Steven Whitehouse", "Fam Zheng", "Csaba Henk", "Alexandre Marangone", "Rik van Riel", "Daniel Veillard", "Dave Jones", "Andreas Gruenbacher", "Karel Zak", "Jan Kratochvil", "Niels de Vos", "Eric Sandeen", "LOPEZ Jean-Charles", "Tamil Muthamizhan", "Jeff Moyer"], "sent": [3938, 2482, 1166, 1029, 988, 737, 511, 383, 328, 277, 265, 238, 180, 179, 148, 147, 107, 78, 49, 46, 44, 34, 32, 29, 28, 27, 24, 20, 20, 19, 16, 14, 13, 13, 11, 11, 10, 10, 7, 7, 7, 6, 6, 5, 5, 4, 4, 3, 3, 3, 2, 2, 2, 2, 2, 2, 2, 2, 2, 1, 1, 1, 1, 1, 1, 1, 1, 1, 1]}, "senders.last month": {"senders": ["Sage Weil", "Gregory Farnum", "Loic Dachary", "Josh Durgin", "Yehuda Sadeh", "Mark Nelson", "Ilya Dryomov", "Samuel Just", "Noah Watkins", "Alfredo Deza", "Joao Eduardo Luis", "Dan Mick", "Travis Rhoden", "jcsp", "John Wilkins", "Patrick McGarry", "Jeff Layton", "David Zafman", "Ken Dreyer", "Josef Bacik", "Yuri Weinstein", "Yan, Zheng", "Kevin Wolf", "Ian Colle", "dhowells", "Daniel P. Berrange", "Avi Kivity", "Ross Turk", "Mike Christie", "Luis Pabon", "Jason Dillaman", "Brad Hubbard", "Eric Blake", "Tyler Brekke", "Douglas Fuller", "Lukas Czerner", "Mauro Carvalho Chehab", "Zack Cerza", "Mehdi Abaakouk", "Mike Snitzer", "Gregory Meno", "Kefu Chai", "Osier Yang", "Anand Avati", "Jeff Darcy", "Christopher R. Hertel", "Paolo Bonzini", "rwheeler", "Giulio Fidente", "Richard Fontana", "Benny Kopilov", "Sandon Van Ness", "Simo Sorce", "chenh", "Steven Whitehouse", "Fam Zheng", "Csaba Henk", "Alexandre Marangone", "Rik van Riel", "Daniel Veillard", "Dave Jones", "Andreas Gruenbacher", "Karel Zak", "Jan Kratochvil", "Niels de Vos", "Eric Sandeen", "LOPEZ Jean-Charles", "Tamil Muthamizhan", "Jeff Moyer"], "sent": [3938, 2482, 1166, 1029, 988, 737, 511, 383, 328, 277, 265, 238, 180, 179, 148, 147, 107, 78, 49, 46, 44, 34, 32, 29, 28, 27, 24, 20, 20, 19, 16, 14, 13, 13, 11, 11, 10, 10, 7, 7, 7, 6, 6, 5, 5, 4, 4, 3, 3, 3, 2, 2, 2, 2, 2, 2, 2, 2, 2, 1, 1, 1, 1, 1, 1, 1, 1, 1, 1]}, "senders.last year": {"senders": ["Sage Weil", "Gregory Farnum", "Loic Dachary", "Josh Durgin", "Yehuda Sadeh", "Mark Nelson", "Ilya Dryomov", "Samuel Just", "Noah Watkins", "Alfredo Deza", "Joao Eduardo Luis", "Dan Mick", "Travis Rhoden", "jcsp", "John Wilkins", "Patrick McGarry", "Jeff Layton", "David Zafman", "Ken Dreyer", "Josef Bacik", "Yuri Weinstein", "Yan, Zheng", "Kevin Wolf", "Ian Colle", "dhowells", "Daniel P. Berrange", "Avi Kivity", "Ross Turk", "Mike Christie", "Luis Pabon", "Jason Dillaman", "Brad Hubbard", "Eric Blake", "Tyler Brekke", "Douglas Fuller", "Lukas Czerner", "Mauro Carvalho Chehab", "Zack Cerza", "Mehdi Abaakouk", "Mike Snitzer", "Gregory Meno", "Kefu Chai", "Osier Yang", "Anand Avati", "Jeff Darcy", "Christopher R. Hertel", "Paolo Bonzini", "rwheeler", "Giulio Fidente", "Richard Fontana", "Benny Kopilov", "Sandon Van Ness", "Simo Sorce", "chenh", "Steven Whitehouse", "Fam Zheng", "Csaba Henk", "Alexandre Marangone", "Rik van Riel", "Daniel Veillard", "Dave Jones", "Andreas Gruenbacher", "Karel Zak", "Jan Kratochvil", "Niels de Vos", "Eric Sandeen", "LOPEZ Jean-Charles", "Tamil Muthamizhan", "Jeff Moyer"], "sent": [3938, 2482, 1166, 1029, 988, 737, 511, 383, 328, 277, 265, 238, 180, 179, 148, 147, 107, 78, 49, 46, 44, 34, 32, 29, 28, 27, 24, 20, 20, 19, 16, 14, 13, 13, 11, 11, 10, 10, 7, 7, 7, 6, 6, 5, 5, 4, 4, 3, 3, 3, 2, 2, 2, 2, 2, 2, 2, 2, 2, 1, 1, 1, 1, 1, 1, 1, 1, 1, 1]}}