{"actions": 120050, "added_lines": 4161267.0, "added_lines_14": 17557.0, "added_lines_180": 889224.0, "added_lines_30": 145578.0, "added_lines_365": 1144908.0, "added_lines_60": 445394.0, "added_lines_7": 9033.0, "added_lines_730": 1549743.0, "added_lines_90": 627214.0, "authors": 273, "authors_14": 39, "authors_180": 113, "authors_30": 53, "authors_365": 158, "authors_60": 70, "authors_7": 31, "authors_730": 196, "authors_90": 85, "avg_commits_author": 155.5333, "avg_commits_month": 362.0172, "avg_files_author": 88.0963, "avg_files_month": 205.0517, "branches": 671, "commits": 41994, "commits_14": 743, "commits_180": 9561, "commits_30": 2437, "commits_365": 16587, "commits_60": 4717, "commits_7": 419, "commits_730": 24815, "commits_90": 5971, "committers": 194, "companies": 45, "companies_2006": 1, "companies_2009": 2, "companies_2012": 18, "core": 11, "diff_netadded_lines_30": -150915, "diff_netadded_lines_365": 740068, "diff_netadded_lines_7": 595, "diff_netauthors_30": 4, "diff_netauthors_365": 74, "diff_netauthors_7": 2, "diff_netcommits_30": 96, "diff_netcommits_365": 7170, "diff_netcommits_7": 76, "diff_netfiles_30": 164, "diff_netfiles_365": 9283, "diff_netfiles_7": 15, "diff_netremoved_lines_30": -19395, "diff_netremoved_lines_365": 245311, "diff_netremoved_lines_7": 1680, "domains": 133, "files": 23786, "files_14": 796, "files_180": 9189, "files_30": 2352, "files_365": 13364, "files_60": 4401, "files_7": 450, "files_730": 16720, "files_90": 5997, "first_date": "2004-06-24", "last_date": "2014-03-12", "occasional": 242, "percentage_added_lines_30": 50, "percentage_added_lines_365": 182, "percentage_added_lines_7": 6, "percentage_authors_30": 8, "percentage_authors_365": 88, "percentage_authors_7": 6, "percentage_commits_30": 4, "percentage_commits_365": 94, "percentage_commits_7": 28, "percentage_files_30": 7, "percentage_files_365": 227, "percentage_files_7": 3, "percentage_removed_lines_30": 27, "percentage_removed_lines_365": 118, "percentage_removed_lines_7": 47, "regular": 17, "removed_lines": 2859364.0, "removed_lines_14": 8706.0, "removed_lines_180": 341381.0, "removed_lines_30": 50125.0, "removed_lines_365": 451501.0, "removed_lines_60": 120065.0, "removed_lines_7": 5171.0, "removed_lines_730": 657680.0, "removed_lines_90": 201573.0, "repositories": 36, "type": "git", "url": "git://github.com/ceph/run-chef-on-sepia.git"}