{"actions": 232591, "added_lines": 9155110.0, "added_lines_30": 36879, "added_lines_365": 1820979, "added_lines_7": 4151, "authors": 627, "authors_30": 72, "authors_365": 340, "authors_7": 30, "avg_commits_author": 133.28, "avg_commits_month": 612.48, "avg_files_author": 115.32, "avg_files_month": 529.96, "branches": 2145, "commits": 80924, "commits_30": 1248, "commits_365": 25347, "commits_7": 152, "committers": 627, "core": 18, "diff_netadded_lines_30": -66657, "diff_netadded_lines_365": -946151, "diff_netadded_lines_7": -2312, "diff_netauthors_30": -12, "diff_netauthors_365": 117, "diff_netauthors_7": 3, "diff_netcommits_30": -971, "diff_netcommits_365": 8356, "diff_netcommits_7": -134, "diff_netfiles_30": -859, "diff_netfiles_365": -6751, "diff_netfiles_7": -560, "diff_netnewauthors_30": -5, "diff_netnewauthors_365": 78, "diff_netnewauthors_7": 1, "diff_netremoved_lines_30": -19643, "diff_netremoved_lines_365": -905020, "diff_netremoved_lines_7": -1903, "domains": 341, "files": 72074, "files_30": 1562, "files_365": 23723, "files_7": 179, "first_date": "2004-06-24", "last_date": "2015-11-05", "newauthors": 627, "newauthors_30": 11, "newauthors_365": 239, "newauthors_7": 1, "occasional": 562, "organizations": 115, "percentage_added_lines_30": 64, "percentage_added_lines_365": 34, "percentage_added_lines_7": 35, "percentage_authors_30": 14, "percentage_authors_365": 52, "percentage_authors_7": 11, "percentage_commits_30": 43, "percentage_commits_365": 49, "percentage_commits_7": 46, "percentage_files_30": 35, "percentage_files_365": 22, "percentage_files_7": 75, "percentage_newauthors_30": 31, "percentage_newauthors_365": 48, "percentage_newauthors_7": 0, "percentage_removed_lines_30": 51, "percentage_removed_lines_365": 50, "percentage_removed_lines_7": 43, "regular": 45, "removed_lines": 5505117.0, "removed_lines_30": 18524, "removed_lines_365": 887069, "removed_lines_7": 2484, "repositories": 46, "type": "git", "url": "git://github.com/ceph/cookbook-vm-general.git"}