{"authors.": {"authors": ["Sage Weil", "Loic Dachary", "John Spray", "Greg Farnum", "Danny Al-Gaaf", "Yehuda Sadeh", "Jason Dillaman", "Samuel Just", "David Zafman", "Alfredo Deza"], "commits": [355, 191, 183, 164, 117, 112, 103, 101, 93, 89], "id": [5, 186, 279, 48, 172, 43, 128084, 69, 174, 226]}, "authors.last month": {"authors": ["Sage Weil", "Greg Farnum", "Loic Dachary", "Danny Al-Gaaf", "John Spray", "Jason Dillaman", "Samuel Just", "Yehuda Sadeh", "Alfredo Deza", "David Zafman"], "commits": [275, 129, 120, 89, 85, 80, 63, 60, 46, 46], "id": [5, 48, 186, 172, 279, 128084, 69, 43, 226, 174]}, "authors.last year": {"authors": ["Sage Weil", "Loic Dachary", "John Spray", "Greg Farnum", "Danny Al-Gaaf", "Yehuda Sadeh", "Jason Dillaman", "Samuel Just", "David Zafman", "Alfredo Deza"], "commits": [355, 191, 183, 164, 117, 112, 103, 101, 93, 89], "id": [5, 186, 279, 48, 172, 43, 128084, 69, 174, 226]}}