{"authors.": {"authors": ["Sage Weil", "John Spray", "Loic Dachary", "David Zafman", "Yehuda Sadeh", "Greg Farnum", "Samuel Just", "Alfredo Deza", "Joao Eduardo Luis", "Yan, Zheng"], "commits": [134, 130, 126, 83, 64, 62, 60, 45, 44, 42], "id": [5, 279, 186, 174, 43, 48, 69, 226, 124, 145]}, "authors.last month": {"authors": ["Sage Weil", "John Spray", "Loic Dachary", "David Zafman", "Yehuda Sadeh", "Greg Farnum", "Samuel Just", "Alfredo Deza", "Joao Eduardo Luis", "Yan, Zheng"], "commits": [134, 130, 126, 83, 64, 62, 60, 45, 44, 42], "id": [5, 279, 186, 174, 43, 48, 69, 226, 124, 145]}, "authors.last year": {"authors": ["Sage Weil", "John Spray", "Loic Dachary", "David Zafman", "Yehuda Sadeh", "Greg Farnum", "Samuel Just", "Alfredo Deza", "Joao Eduardo Luis", "Yan, Zheng"], "commits": [134, 130, 126, 83, 64, 62, 60, 45, 44, 42], "id": [5, 279, 186, 174, 43, 48, 69, 226, 124, 145]}}