{"diff_netdownloads_30": -475157, "diff_netdownloads_365": 3720868, "diff_netdownloads_7": 0, "diff_netpackages_30": -11361, "diff_netpackages_365": -719, "diff_netpackages_7": 0, "downloads": 1164983, "downloads_30": 0, "downloads_365": 4983764, "downloads_7": 0, "first_date": "2012-07-20", "ips": 9092, "last_date": "2014-11-26", "packages": 16821, "packages_30": 0, "packages_365": 27365, "packages_7": 0, "percentage_downloads_30": 100, "percentage_downloads_365": 294, "percentage_downloads_7": 0, "percentage_packages_30": 100, "percentage_packages_365": 2, "percentage_packages_7": 0, "protocols": 1}