{"actions": 5721, "added_lines": 81850.0, "added_lines_30": 127117, "added_lines_365": 1653641, "added_lines_7": 8, "authors": 6, "authors_30": 6, "authors_365": 7, "authors_7": 1, "avg_commits_author": 372.6667, "avg_commits_month": 1118.0, "avg_files_author": 269.0, "avg_files_month": 807.0, "branches": 173, "commits": 2236, "commits_30": 845, "commits_365": 7557, "commits_7": 1, "committers": 6, "diff_netadded_lines_30": 15609, "diff_netadded_lines_365": 927677, "diff_netadded_lines_7": -21174, "diff_netauthors_30": 0, "diff_netauthors_365": -4, "diff_netauthors_7": -5, "diff_netcommits_30": -14, "diff_netcommits_365": 985, "diff_netcommits_7": -205, "diff_netfiles_30": 151, "diff_netfiles_365": 2165, "diff_netfiles_7": -231, "diff_netremoved_lines_30": 14864, "diff_netremoved_lines_365": 1088511, "diff_netremoved_lines_7": -8196, "files": 1614, "files_30": 731, "files_365": 7151, "files_7": 1, "first_date": "2014-10-01", "last_date": "2014-12-26", "percentage_added_lines_30": 13, "percentage_added_lines_365": 127, "percentage_added_lines_7": 99, "percentage_authors_30": 0, "percentage_authors_365": 36, "percentage_authors_7": 83, "percentage_commits_30": 1, "percentage_commits_365": 14, "percentage_commits_7": 99, "percentage_files_30": 26, "percentage_files_365": 43, "percentage_files_7": 99, "percentage_removed_lines_30": 43, "percentage_removed_lines_365": 336, "percentage_removed_lines_7": 100, "removed_lines": 35010.0, "removed_lines_30": 48864, "removed_lines_365": 1412376, "removed_lines_7": 0, "repositories": 7}