{"authors.": {"authors": ["Sage Weil", "Loic Dachary", "Danny Al-Gaaf", "John Spray", "Greg Farnum", "Alfredo Deza", "Yehuda Sadeh", "David Zafman", "Samuel Just", "Jason Dillaman"], "commits": [687.0, 263.0, 212.0, 210.0, 196.0, 172.0, 157.0, 147.0, 131.0, 130.0], "id": [5, 186, 172, 279, 48, 226, 43, 174, 69, 128084]}, "authors.last month": {"authors": ["Sage Weil", "Danny Al-Gaaf", "Loic Dachary", "Greg Farnum", "Alfredo Deza", "Jason Dillaman", "Yehuda Sadeh", "John Spray", "David Zafman", "Zack Cerza"], "commits": [543.0, 133.0, 133.0, 126.0, 96.0, 93.0, 87.0, 86.0, 79.0, 68.0], "id": [5, 172, 186, 48, 226, 128084, 43, 279, 174, 355]}, "authors.last year": {"authors": ["Sage Weil", "Loic Dachary", "Danny Al-Gaaf", "John Spray", "Greg Farnum", "Alfredo Deza", "Yehuda Sadeh", "David Zafman", "Samuel Just", "Jason Dillaman"], "commits": [687.0, 263.0, 212.0, 210.0, 196.0, 172.0, 157.0, 147.0, 131.0, 130.0], "id": [5, 186, 172, 279, 48, 226, 43, 174, 69, 128084]}}