{"actions": 17238, "added_lines": 361582.0, "added_lines_30": 134165, "added_lines_365": 2837535, "added_lines_7": 4013, "authors": 105, "authors_30": 67, "authors_365": 237, "authors_7": 15, "avg_commits_author": 60.7788, "avg_commits_month": 3160.5, "avg_files_author": 69.4327, "avg_files_month": 3610.5, "branches": 424, "commits": 6321, "commits_30": 2442, "commits_365": 21785, "commits_7": 156, "committers": 105, "companies": 26, "core": 14, "diff_netadded_lines_30": 19397, "diff_netadded_lines_365": 559931, "diff_netadded_lines_7": -19241, "diff_netauthors_30": -4, "diff_netauthors_365": 92, "diff_netauthors_7": -24, "diff_netcommits_30": 587, "diff_netcommits_365": 7661, "diff_netcommits_7": -365, "diff_netfiles_30": 75, "diff_netfiles_365": 12804, "diff_netfiles_7": -437, "diff_netremoved_lines_30": 15386, "diff_netremoved_lines_365": 1819160, "diff_netremoved_lines_7": -7319, "domains": 56, "files": 7221, "files_30": 2304, "files_365": 29331, "files_7": 128, "first_date": "2014-10-01", "last_date": "2014-12-31", "occasional": 76, "percentage_added_lines_30": 16, "percentage_added_lines_365": 24, "percentage_added_lines_7": 82, "percentage_authors_30": 5, "percentage_authors_365": 63, "percentage_authors_7": 61, "percentage_commits_30": 31, "percentage_commits_365": 54, "percentage_commits_7": 70, "percentage_files_30": 3, "percentage_files_365": 77, "percentage_files_7": 77, "percentage_removed_lines_30": 42, "percentage_removed_lines_365": 350, "percentage_removed_lines_7": 81, "regular": 20, "removed_lines": 145812.0, "removed_lines_30": 51671, "removed_lines_365": 2338281, "removed_lines_7": 1677, "repositories": 23, "type": "git", "url": "git://github.com/ceph/run-chef-on-sepia.git"}