{"senders.": {"id": [48, 5, 229890, 224533, 225672, 224247, 279, 225477, 222, 186], "senders": ["Greg Farnum", "Sage Weil", "lindsay.mathieson-Re5JQEeQqe8AvxtiuMwx3w@public.gmane.org", "chibi-FW+hd8ioUD0@public.gmane.org", "robert-4JaGZRWAfWbajFs6igw21g@public.gmane.org", "aderumier-U/x3PoR4x10AvxtiuMwx3w@public.gmane.org", "John Spray", "nick-ksME7r3P/wO1Qrn1Bg8BZw@public.gmane.org", "Mark Nelson", "Loic Dachary"], "sent": [96, 65, 64, 57, 43, 39, 36, 30, 29, 27]}, "senders.last month": {"id": [48, 5, 224247, 222, 230576, 225672, 279, 226076, 114, 224533], "senders": ["Greg Farnum", "Sage Weil", "aderumier-U/x3PoR4x10AvxtiuMwx3w@public.gmane.org", "Mark Nelson", "super.iterator-Re5JQEeQqe8AvxtiuMwx3w@public.gmane.org", "robert-4JaGZRWAfWbajFs6igw21g@public.gmane.org", "John Spray", "xschen-O5mkAQvHD1yPt1CcHtbs0g@public.gmane.org", "Florian Haas", "chibi-FW+hd8ioUD0@public.gmane.org"], "sent": [45, 43, 35, 22, 22, 19, 18, 17, 16, 12]}, "senders.last year": {"id": [48, 5, 229890, 224533, 225672, 224247, 279, 225477, 222, 186], "senders": ["Greg Farnum", "Sage Weil", "lindsay.mathieson-Re5JQEeQqe8AvxtiuMwx3w@public.gmane.org", "chibi-FW+hd8ioUD0@public.gmane.org", "robert-4JaGZRWAfWbajFs6igw21g@public.gmane.org", "aderumier-U/x3PoR4x10AvxtiuMwx3w@public.gmane.org", "John Spray", "nick-ksME7r3P/wO1Qrn1Bg8BZw@public.gmane.org", "Mark Nelson", "Loic Dachary"], "sent": [96, 65, 64, 57, 43, 39, 36, 30, 29, 27]}}